[{"stage":"Mushroom Kingdom","name":"Mushroom Kingdom","lvd":"mario_past64_00","collisions":[{"name":"COL_curve1","vertex":[[-255.0,0.0],[-29.1880054,0.0],[-29.1880054,-205.0],[-255.0,-205.0],[-255.0,0.0]],"materials":[{"leftLedge":false,"rightLedge":true,"noWallJump":false,"passthroughAngle":90,"length":225.812,"ceiling":false,"wall":false,"material":"Brick"},{"leftLedge":false,"rightLedge":false,"noWallJump":false,"passthroughAngle":0,"length":205.0,"ceiling":false,"wall":true,"material":"Brick"},{"leftLedge":false,"rightLedge":false,"noWallJump":false,"passthroughAngle":270,"length":225.812,"ceiling":true,"wall":false,"material":"Brick"},{"leftLedge":false,"rightLedge":false,"noWallJump":false,"passthroughAngle":180,"length":205.0,"ceiling":false,"wall":true,"material":"Brick"}],"boundingBox":[[-255.0,-205.0],[-29.1880054,0.0]]},{"name":"COL_curve2","vertex":[[255.0,0.0],[255.0,-205.0],[28.75185,-205.0],[28.75185,0.0],[91.35962,0.0],[91.34405,7.96020842],[110.5455,7.96020842],[110.523605,0.0],[255.0,0.0]],"materials":[{"leftLedge":false,"rightLedge":false,"noWallJump":false,"passthroughAngle":0,"length":205.0,"ceiling":false,"wall":true,"material":"Brick"},{"leftLedge":false,"rightLedge":false,"noWallJump":false,"passthroughAngle":270,"length":226.248154,"ceiling":true,"wall":false,"material":"Brick"},{"leftLedge":false,"rightLedge":false,"noWallJump":false,"passthroughAngle":180,"length":205.0,"ceiling":false,"wall":true,"material":"Brick"},{"leftLedge":true,"rightLedge":false,"noWallJump":false,"passthroughAngle":90,"length":62.60777,"ceiling":false,"wall":false,"material":"Brick"},{"leftLedge":false,"rightLedge":false,"noWallJump":false,"passthroughAngle":181,"length":7.96022367,"ceiling":false,"wall":true,"material":"Brick"},{"leftLedge":false,"rightLedge":false,"noWallJump":false,"passthroughAngle":90,"length":19.2014542,"ceiling":false,"wall":false,"material":"Brick"},{"leftLedge":false,"rightLedge":false,"noWallJump":false,"passthroughAngle":0,"length":7.96023846,"ceiling":false,"wall":true,"material":"Brick"},{"leftLedge":false,"rightLedge":false,"noWallJump":false,"passthroughAngle":90,"length":144.4764,"ceiling":false,"wall":false,"material":"Brick"}],"boundingBox":[[28.75185,-205.0],[255.0,7.96020842]]},{"name":"COL_curve3","vertex":[[-253.822586,53.5282364],[-253.822586,43.5282364],[-83.52824,43.5282364],[-83.42343,56.757206],[-82.7816544,68.98801],[-82.7725143,73.52824],[-101.203362,73.52824],[-101.218109,68.9752045],[-100.089859,56.5343437],[-99.79963,53.5282364],[-253.822586,53.5282364]],"materials":[{"leftLedge":false,"rightLedge":false,"noWallJump":false,"passthroughAngle":180,"length":10.0,"ceiling":false,"wall":true,"material":"Brick"},{"leftLedge":false,"rightLedge":false,"noWallJump":false,"passthroughAngle":270,"length":170.294342,"ceiling":true,"wall":false,"material":"Brick"},{"leftLedge":false,"rightLedge":false,"noWallJump":false,"passthroughAngle":0,"length":13.2293844,"ceiling":false,"wall":true,"material":"Brick"},{"leftLedge":false,"rightLedge":false,"noWallJump":false,"passthroughAngle":357,"length":12.2476273,"ceiling":false,"wall":true,"material":"Brick"},{"leftLedge":false,"rightLedge":false,"noWallJump":false,"passthroughAngle":0,"length":4.540239,"ceiling":false,"wall":true,"material":"Brick"},{"leftLedge":false,"rightLedge":false,"noWallJump":false,"passthroughAngle":90,"length":18.4308472,"ceiling":false,"wall":false,"material":"Brick"},{"leftLedge":false,"rightLedge":false,"noWallJump":false,"passthroughAngle":179,"length":4.553056,"ceiling":false,"wall":false,"material":"Brick"},{"leftLedge":false,"rightLedge":false,"noWallJump":false,"passthroughAngle":186,"length":12.4919157,"ceiling":false,"wall":true,"material":"Brick"},{"leftLedge":false,"rightLedge":false,"noWallJump":false,"passthroughAngle":186,"length":3.020085,"ceiling":false,"wall":true,"material":"Brick"},{"leftLedge":false,"rightLedge":false,"noWallJump":false,"passthroughAngle":90,"length":154.022949,"ceiling":false,"wall":false,"material":"Brick"}],"boundingBox":[[-253.822586,43.5282364],[-82.7725143,73.52824]]},{"name":"COL_LiftL","vertex":[[-12.4764442,0.0125584546],[12.4764442,0.0125584546]],"materials":[{"leftLedge":false,"rightLedge":false,"noWallJump":false,"passthroughAngle":90,"length":24.9528885,"ceiling":false,"wall":false,"material":"Brick"}],"boundingBox":[[-12.4764442,0.0125584546],[12.4764442,0.0125584546]]},{"name":"COL_LiftR","vertex":[[-12.4764442,0.0125584546],[12.4764442,0.0125584546]],"materials":[{"leftLedge":false,"rightLedge":false,"noWallJump":false,"passthroughAngle":90,"length":24.9528885,"ceiling":false,"wall":false,"material":"Brick"}],"boundingBox":[[-12.4764442,0.0125584546],[12.4764442,0.0125584546]]}],"platforms":[{"name":"COL_curve8","vertex":[[53.29997,53.8861],[86.62146,53.8861]],"materials":[{"leftLedge":false,"rightLedge":false,"noWallJump":false,"passthroughAngle":90,"length":0.0,"ceiling":false,"wall":false,"material":"Brick"}],"boundingBox":[[53.29997,53.8861],[86.62146,53.8861]]},{"name":"COL_curve6","vertex":[[38.41203,26.3255081],[76.57478,26.3255081]],"materials":[{"leftLedge":false,"rightLedge":false,"noWallJump":false,"passthroughAngle":90,"length":0.0,"ceiling":false,"wall":false,"material":"Brick"}],"boundingBox":[[38.41203,26.3255081],[76.57478,26.3255081]]},{"name":"COL_curve7","vertex":[[-67.6112442,38.90515],[-29.1042156,38.90515]],"materials":[{"leftLedge":false,"rightLedge":false,"noWallJump":false,"passthroughAngle":90,"length":0.0,"ceiling":false,"wall":false,"material":"Brick"}],"boundingBox":[[-67.6112442,38.90515],[-29.1042156,38.90515]]}],"blast_zones":[-210.0,210.0,189.699448,-101.681358],"camera":[-150.0,150.0,135.0,-54.9999962],"center":[0.0,0.0125584546],"spawns":[[-50.0,0.0],[60.0,0.0],[100.841507,8.44162],[-85.0,0.0],[130.0,0.0],[-120.0,0.0],[-48.36875,38.75888],[56.71544,26.7154369]],"respawns":[[0.0,90.0],[40.0,90.0],[-40.0,90.0],[80.0,90.0],[-20.0,110.0],[20.0,110.0],[-60.0,110.0],[60.0,110.0]],"items":[]}]