[
  {
    "stage": "Omega Mario Circuit (Brawl)",
    "name": "Mario Circuit (Brawl)",
    "lvd": "Z_XKart_00",
    "collisions": [
      {
        "name": "COL_00_Floor01",
        "vertex": [
          [
            -71.1692047,
            -16.8729534
          ],
          [
            -86.9,
            -5.673242
          ],
          [
            -86.9,
            0.0
          ],
          [
            -81.9,
            0.0
          ],
          [
            81.9,
            0.0
          ],
          [
            86.9,
            0.0
          ],
          [
            86.9,
            -5.673242
          ],
          [
            71.1692047,
            -16.8729534
          ],
          [
            -71.1692047,
            -16.8729534
          ]
        ],
        "materials": [
          {
            "leftLedge": false,
            "rightLedge": false,
            "noWallJump": false,
            "passthroughAngle": 235,
            "length": 19.3103981,
            "ceiling": false,
            "wall": true,
            "material": "Brick"
          },
          {
            "leftLedge": false,
            "rightLedge": false,
            "noWallJump": false,
            "passthroughAngle": 180,
            "length": 5.673242,
            "ceiling": false,
            "wall": true,
            "material": "Brick"
          },
          {
            "leftLedge": true,
            "rightLedge": false,
            "noWallJump": false,
            "passthroughAngle": 90,
            "length": 5.0,
            "ceiling": false,
            "wall": false,
            "material": "Brick"
          },
          {
            "leftLedge": false,
            "rightLedge": false,
            "noWallJump": false,
            "passthroughAngle": 90,
            "length": 163.8,
            "ceiling": false,
            "wall": false,
            "material": "Brick"
          },
          {
            "leftLedge": false,
            "rightLedge": true,
            "noWallJump": false,
            "passthroughAngle": 90,
            "length": 5.0,
            "ceiling": false,
            "wall": false,
            "material": "Brick"
          },
          {
            "leftLedge": false,
            "rightLedge": false,
            "noWallJump": false,
            "passthroughAngle": 0,
            "length": 5.673242,
            "ceiling": false,
            "wall": true,
            "material": "Brick"
          },
          {
            "leftLedge": false,
            "rightLedge": false,
            "noWallJump": false,
            "passthroughAngle": 306,
            "length": 19.3103981,
            "ceiling": false,
            "wall": true,
            "material": "Brick"
          },
          {
            "leftLedge": false,
            "rightLedge": false,
            "noWallJump": false,
            "passthroughAngle": 270,
            "length": 142.338409,
            "ceiling": true,
            "wall": false,
            "material": "Brick"
          }
        ],
        "boundingBox": [
          [
            -86.9,
            -16.8729534
          ],
          [
            86.9,
            0.0
          ]
        ]
      }
    ],
    "platforms": [],
    "blast_zones": [
      -240.0,
      240.000031,
      180.000015,
      -115.0
    ],
    "camera": [
      -180.0,
      180.0,
      130.0,
      -60.0000153
    ],
    "center": [
      0.0,
      0.0
    ],
    "spawns": [
      [
        -60.0,
        0.0
      ],
      [
        60.0,
        0.0
      ],
      [
        -20.0,
        0.0
      ],
      [
        20.0,
        0.0
      ],
      [
        -40.0,
        0.0
      ],
      [
        40.0,
        0.0
      ],
      [
        -80.0,
        0.0
      ],
      [
        80.0,
        0.0
      ]
    ],
    "respawns": [
      [
        0.0,
        50.0
      ],
      [
        36.0,
        50.0
      ],
      [
        -36.0,
        50.0
      ],
      [
        72.0,
        50.0
      ],
      [
        -18.0,
        78.0
      ],
      [
        18.0,
        78.0
      ],
      [
        -54.0,
        78.0
      ],
      [
        54.0,
        78.0
      ]
    ],
    "items": [
      {
        "name": "ItemPopup__tag_IPP0001_00_item0",
        "subname": "_tag_IPP0001_00_item01",
        "sections": [
          {
            "points": [
              [
                -80.0,
                50.0
              ],
              [
                80.0,
                50.0
              ]
            ]
          },
          {
            "points": [
              [
                -80.0,
                100.0
              ],
              [
                80.0,
                100.0
              ]
            ]
          }
        ]
      }
    ]
  }
]