{"V1":"13.0.0","V2":"13.0.1","Diffs":{"Diffs":{"ike":[{"Filename":"game_Attack13.txt","Type":0,"DiffPath":"ike/ike/game_Attack13.txt.diff"},{"Filename":"game_AttackHi4.txt","Type":0,"DiffPath":"ike/ike/game_AttackHi4.txt.diff"},{"Filename":"game_SpecialSAttack.txt","Type":0,"DiffPath":"ike/ike/game_SpecialSAttack.txt.diff"},{"Filename":"game_FinalStart.txt","Type":0,"DiffPath":"ike/ike/game_FinalStart.txt.diff"},{"Filename":"game_FinalAirStart.txt","Type":0,"DiffPath":"ike/ike/game_FinalAirStart.txt.diff"}],"ike_sword":[]},"Name":"ike"}}