{"V1":"7.0.0","V2":"8.0.0","Diffs":{"Diffs":{"szerosuit":[{"Filename":"game_AttackHi4.txt","Type":0,"DiffPath":"szerosuit/szerosuit/game_AttackHi4.txt.diff"},{"Filename":"game_FinalStart.txt","Type":0,"DiffPath":"szerosuit/szerosuit/game_FinalStart.txt.diff"},{"Filename":"game_FinalAirStart.txt","Type":0,"DiffPath":"szerosuit/szerosuit/game_FinalAirStart.txt.diff"}],"szerosuit_laser":[],"szerosuit_paralyzer_bullet":[],"szerosuit_reticle":[{"Filename":"game_FinalEnd.txt","Type":0,"DiffPath":"szerosuit/szerosuit_reticle/game_FinalEnd.txt.diff"}],"szerosuit_whip":[]},"Name":"szerosuit"}}